cbr_currency_api-0.1.0.dist-info/licenses/LICENCE
crb_currency_api/__init__.py
crb_currency_api/api.py
crb_currency_api/baseAPI.py
cbr_currency_api-0.1.0.dist-info/METADATA
cbr_currency_api-0.1.0.dist-info/WHEEL
cbr_currency_api-0.1.0.dist-info/top_level.txt
cbr_currency_api-0.1.0.dist-info/RECORD
